great_expectations_ethical_ai_expectations/__init__.py
great_expectations_ethical_ai_expectations/expectations/__init__.py
great_expectations_ethical_ai_expectations/expectations/expect_table_binary_label_model_bias.py
great_expectations_ethical_ai_expectations/expectations/expect_table_linear_feature_importances_to_be.py
great_expectations_ethical_ai_expectations/metrics/__init__.py
great_expectations_ethical_ai_expectations/profilers/__init__.py
great_expectations_ethical_ai_expectations-0.1.0.dist-info/LICENSE
great_expectations_ethical_ai_expectations-0.1.0.dist-info/METADATA
great_expectations_ethical_ai_expectations-0.1.0.dist-info/WHEEL
great_expectations_ethical_ai_expectations-0.1.0.dist-info/top_level.txt
great_expectations_ethical_ai_expectations-0.1.0.dist-info/RECORD
