Metadata-Version: 2.1
Name: great-expectations-ethical-ai-expectations
Version: 0.1.0
Summary: A collection of Expectations to validate for degradation, bias, and related Ethical Data concerns with Great Expectations.
Author: Great Expectations
Author-email: austin@greatexpectations.io
License-File: LICENSE
Requires-Dist: aequitas
Requires-Dist: great-expectations
Requires-Dist: pandas
Requires-Dist: scikit-learn
Requires-Dist: setuptools
